{
  "name": "irons_spellbooks:catacombs_hallway_pool",
  "fallback": "irons_spellbooks:catacombs_fallback_pool",
  "elements": [
    {
      "weight": 2,
      "element": {
        "location": "irons_spellbooks:catacombs/hallway_straight",
        "processors": "irons_spellbooks:catacombs_randomization",
        "projection": "rigid",
        "element_type": "minecraft:single_pool_element"
      }
    },
    {
      "weight": 1,
      "element": {
        "location": "irons_spellbooks:catacombs/hallway_straight_trapped",
        "processors": "irons_spellbooks:catacombs_randomization",
        "projection": "rigid",
        "element_type": "minecraft:single_pool_element"
      }
    },
    {
      "weight": 3,
      "element": {
        "location": "irons_spellbooks:catacombs/hallway_straight_2",
        "processors": "irons_spellbooks:catacombs_randomization",
        "projection": "rigid",
        "element_type": "minecraft:single_pool_element"
      }
    },
    {
      "weight": 3,
      "element": {
        "location": "irons_spellbooks:catacombs/hallway_tee_1",
        "processors": "irons_spellbooks:catacombs_randomization",
        "projection": "rigid",
        "element_type": "minecraft:single_pool_element"
      }
    },
    {
      "weight": 3,
      "element": {
        "location": "irons_spellbooks:catacombs/hallway_tee_2",
        "processors": "irons_spellbooks:catacombs_randomization",
        "projection": "rigid",
        "element_type": "minecraft:single_pool_element"
      }
    },
    {
      "weight": 6,
      "element": {
        "location": "irons_spellbooks:catacombs/hallway_turn_1",
        "processors": "irons_spellbooks:catacombs_randomization",
        "projection": "rigid",
        "element_type": "minecraft:single_pool_element"
      }
    },
    {
      "weight": 4,
      "element": {
        "location": "irons_spellbooks:catacombs/hallway_spiral_stairs",
        "processors": "irons_spellbooks:catacombs_randomization",
        "projection": "rigid",
        "element_type": "minecraft:single_pool_element"
      }
    },
    {
      "weight": 3,
      "element": {
        "location": "irons_spellbooks:catacombs/hallway_rope_bridge",
        "processors": "irons_spellbooks:catacombs_randomization",
        "projection": "rigid",
        "element_type": "minecraft:single_pool_element"
      }
    },
    {
      "weight": 4,
      "element": {
        "location": "irons_spellbooks:catacombs/hallway_stairway",
        "processors": "irons_spellbooks:catacombs_randomization",
        "projection": "rigid",
        "element_type": "minecraft:single_pool_element"
      }
    }
  ]
}
