{
  "name": "irons_spellbooks:battleground_start_pool",
  "fallback": "minecraft:empty",
  "elements": [
    {
      "weight": 1,
      "element": {
        "location": "irons_spellbooks:battleground/decorations/burial_1",
        "processors": "irons_spellbooks:ancient_battlegrounds_randomization",
        "projection": "rigid",
        "element_type": "minecraft:single_pool_element"
      }
    },
    {
      "weight": 1,
      "element": {
        "location": "irons_spellbooks:battleground/decorations/burial_2",
        "processors": "irons_spellbooks:ancient_battlegrounds_randomization",
        "projection": "rigid",
        "element_type": "minecraft:single_pool_element"
      }
    },
    {
      "weight": 1,
      "element": {
        "location": "irons_spellbooks:battleground/decorations/burial_3",
        "processors": "irons_spellbooks:ancient_battlegrounds_randomization",
        "projection": "rigid",
        "element_type": "minecraft:single_pool_element"
      }
    },
    {
      "weight": 1,
      "element": {
        "location": "irons_spellbooks:battleground/decorations/burial_4",
        "processors": "irons_spellbooks:ancient_battlegrounds_randomization",
        "projection": "rigid",
        "element_type": "minecraft:single_pool_element"
      }
    },
    {
      "weight": 4,
      "element": {
        "location": "irons_spellbooks:battleground/decorations/armor_1",
        "processors": "irons_spellbooks:ancient_battlegrounds_randomization",
        "projection": "rigid",
        "element_type": "minecraft:single_pool_element"
      }
    },
    {
      "weight": 3,
      "element": {
        "location": "irons_spellbooks:battleground/decorations/armor_2",
        "processors": "irons_spellbooks:ancient_battlegrounds_randomization",
        "projection": "rigid",
        "element_type": "minecraft:single_pool_element"
      }
    },
    {
      "weight": 1,
      "element": {
        "location": "irons_spellbooks:battleground/decorations/banner",
        "processors": "irons_spellbooks:ancient_battlegrounds_randomization",
        "projection": "rigid",
        "element_type": "minecraft:single_pool_element"
      }
    },
    {
      "weight": 1,
      "element": {
        "location": "irons_spellbooks:battleground/decorations/banner_2",
        "processors": "irons_spellbooks:ancient_battlegrounds_randomization",
        "projection": "rigid",
        "element_type": "minecraft:single_pool_element"
      }
    },
    {
      "weight": 1,
      "element": {
        "location": "irons_spellbooks:battleground/decorations/wall_1",
        "processors": "irons_spellbooks:ancient_battlegrounds_randomization",
        "projection": "rigid",
        "element_type": "minecraft:single_pool_element"
      }
    },
    {
      "weight": 4,
      "element": {
        "location": "irons_spellbooks:battleground/decorations/wall_2",
        "processors": "irons_spellbooks:ancient_battlegrounds_randomization",
        "projection": "rigid",
        "element_type": "minecraft:single_pool_element"
      }
    },
    {
      "weight": 1,
      "element": {
        "location": "irons_spellbooks:battleground/decorations/wall_3",
        "processors": "irons_spellbooks:ancient_battlegrounds_randomization",
        "projection": "rigid",
        "element_type": "minecraft:single_pool_element"
      }
    },
    {
      "weight": 1,
      "element": {
        "location": "irons_spellbooks:battleground/decorations/wall_4",
        "processors": "irons_spellbooks:ancient_battlegrounds_randomization",
        "projection": "rigid",
        "element_type": "minecraft:single_pool_element"
      }
    },
    {
      "weight": 1,
      "element": {
        "location": "irons_spellbooks:battleground/decorations/wall_5",
        "processors": "irons_spellbooks:ancient_battlegrounds_randomization",
        "projection": "rigid",
        "element_type": "minecraft:single_pool_element"
      }
    },
    {
      "weight": 1,
      "element": {
        "location": "irons_spellbooks:battleground/decorations/wall_6",
        "processors": "irons_spellbooks:ancient_battlegrounds_randomization",
        "projection": "rigid",
        "element_type": "minecraft:single_pool_element"
      }
    },
    {
      "weight": 4,
      "element": {
        "location": "irons_spellbooks:battleground/decorations/wall_7",
        "processors": "irons_spellbooks:ancient_battlegrounds_randomization",
        "projection": "rigid",
        "element_type": "minecraft:single_pool_element"
      }
    },
    {
      "weight": 1,
      "element": {
        "location": "irons_spellbooks:battleground/decorations/fossil",
        "processors": "irons_spellbooks:ancient_battlegrounds_randomization",
        "projection": "rigid",
        "element_type": "minecraft:single_pool_element"
      }
    },
    {
      "weight": 1,
      "element": {
        "location": "irons_spellbooks:battleground/decorations/skull_pile",
        "processors": "irons_spellbooks:ancient_battlegrounds_randomization",
        "projection": "rigid",
        "element_type": "minecraft:single_pool_element"
      }
    },
    {
      "weight": 1,
      "element": {
        "location": "irons_spellbooks:battleground/decorations/hill_1",
        "processors": "irons_spellbooks:ancient_battlegrounds_randomization",
        "projection": "rigid",
        "element_type": "minecraft:single_pool_element"
      }
    },
    {
      "weight": 1,
      "element": {
        "location": "irons_spellbooks:battleground/decorations/hill_2",
        "processors": "irons_spellbooks:ancient_battlegrounds_randomization",
        "projection": "rigid",
        "element_type": "minecraft:single_pool_element"
      }
    },
    {
      "weight": 1,
      "element": {
        "location": "irons_spellbooks:battleground/decorations/hill_3",
        "processors": "irons_spellbooks:ancient_battlegrounds_randomization",
        "projection": "rigid",
        "element_type": "minecraft:single_pool_element"
      }
    },
    {
      "weight": 2,
      "element": {
        "location": "irons_spellbooks:battleground/decorations/piglin_camp",
        "processors": "irons_spellbooks:ancient_battlegrounds_randomization",
        "projection": "rigid",
        "element_type": "minecraft:single_pool_element"
      }
    }
  ]
}
